setup.py
src/impaf_sqlalchemy.egg-info/PKG-INFO
src/impaf_sqlalchemy.egg-info/SOURCES.txt
src/impaf_sqlalchemy.egg-info/dependency_links.txt
src/impaf_sqlalchemy.egg-info/namespace_packages.txt
src/impaf_sqlalchemy.egg-info/not-zip-safe
src/impaf_sqlalchemy.egg-info/requires.txt
src/impaf_sqlalchemy.egg-info/top_level.txt
src/implugin/__init__.py
src/implugin/sqlalchemy/__init__.py
src/implugin/sqlalchemy/application.py
src/implugin/sqlalchemy/driver.py
src/implugin/sqlalchemy/generator.py
src/implugin/sqlalchemy/requestable.py
src/implugin/sqlalchemy/testing.py
src/implugin/sqlalchemy/tests/__init__.py
src/implugin/sqlalchemy/tests/test_application.py
src/implugin/sqlalchemy/tests/test_driver.py
src/implugin/sqlalchemy/tests/test_requestable.py