Metadata-Version: 1.0
Name: impaf-sqlalchemy
Version: 0.1
Summary: SQLAlchemy plugin for Impaf.
Home-page: UNKNOWN
Author: UNKNOWN
Author-email: UNKNOWN
License: Apache License 2.0
Platform: UNKNOWN
